And_Gate/and_dataflow.v
`timescale 1ns/1ns
module and_gate_df(input a,b, output y);
   assign y= a & b;
endmodule

And_Gate/and_testbench.v
`timescale 1ns/1ns

module and_tb;
   reg a,b;
   wire y;
   and_gate_df dut(.a(a),.b(b),.y(y));

   initial begin
      $dumpfile("waveform.vcd");
      $dumpvars(0,and_tb);

     $monitor("time=%0t INPUT: a=%b b=%b OUTPUT: y=%b", $time, a, b, y);
      
      a=0; b=0;
      #10 a=0; b=1;
      #10 a=1; b=0;
      #10 a=1; b=1;
      #10 a=0; b=1;
      #10 a=1; b=1;
      #10 a=0; b=0;
      #10 a=1; b=1;
      #100 $finish;
   end
endmodule

And_Gate/waveform.vcd
$date
	Thu Jun 05 14:49:32 2025
$end
$version
	Icarus Verilog
$end
$timescale
	1ns
$end
$scope module and_tb $end
$var wire 1 ! y $end
$var reg 1 " a $end
$var reg 1 # b $end
$scope module dut $end
$var wire 1 $ a $end
$var wire 1 % b $end
$var wire 1 ! y $end
$upscope $end
$upscope $end
$enddefinitions $end
#0
$dumpvars
0%
0$
0#
0"
0!
$end
#10
1#
1%
#20
0#
0%
1"
1$
#30
1!
1#
1%
#40
0!
0"
0$
#50
1!
1"
1$
#60
0!
0#
0%
0"
0$
#70
1!
1#
1%
1"
1$
